MANIFEST.in
manage.py
setup.py
app/__init__.py
app/database/__init__.py
app/database/base.py
app/database/model.py
app/static/dist/redis-monitor.bundle.js
app/static/res/css/style.css
app/static/res/img/favicon.png
app/templates/index_page.html
app/utils/JsonUtil.py
app/utils/RedisMonitor.py
app/utils/RedisUtil.py
app/utils/RequestUtil.py
app/utils/ResponseUtil.py
app/utils/StringUtil.py
app/utils/__init__.py
app/views/__init__.py
app/views/main_views.py
app/wraps/__init__.py
app/wraps/singleton_wrap.py
app/wraps/wrapcache.py
doc/shot_1.png
doc/shot_2.png
doc/shot_3.png
doc/shot_4.png
redis_monitor.egg-info/PKG-INFO
redis_monitor.egg-info/SOURCES.txt
redis_monitor.egg-info/dependency_links.txt
redis_monitor.egg-info/entry_points.txt
redis_monitor.egg-info/not-zip-safe
redis_monitor.egg-info/requires.txt
redis_monitor.egg-info/top_level.txt