Metadata-Version: 1.1
Name: redis-monitor
Version: 1.0.3
Summary: 使用Flask开发的一个 web 可视化的 redis 监控程序，可以查看 redis 的服务器信息、实时监控 redis 的消息处理 ops、内存占用、cpu 消耗，以及 redis 联通时间。 A web visualization redis monitoring program. Performance optimized and very easy to install and deploy. the monitor data come from redis.info().
Home-page: https://github.com/hustcc
Author: hustcc
Author-email: vip@hust.edu.cn
License: MIT
Keywords: redis,monitor,redis-monitor,redis client,redis usage
Platform: UNKNOWN
Classifier: Intended Audience :: Developers
Classifier: Operating System :: OS Independent
Classifier: Natural Language :: Chinese (Simplified)
Classifier: Programming Language :: Python
Classifier: Programming Language :: Python :: 2
Classifier: Programming Language :: Python :: 2.5
Classifier: Programming Language :: Python :: 2.6
Classifier: Programming Language :: Python :: 2.7
Classifier: Programming Language :: Python :: 3
Classifier: Programming Language :: Python :: 3.5
Classifier: Programming Language :: Python :: 3.6
Classifier: Topic :: Software Development
Classifier: Topic :: Utilities
